ZJFootballAutoSign/__init__.py
ZJFootballAutoSign/signIn.py
ZJFootballAutoSign-0.1.3.dist-info/LICENSE
ZJFootballAutoSign-0.1.3.dist-info/METADATA
ZJFootballAutoSign-0.1.3.dist-info/WHEEL
ZJFootballAutoSign-0.1.3.dist-info/top_level.txt
ZJFootballAutoSign-0.1.3.dist-info/RECORD
